cloud_governance/__init__.py
cloud_governance/cloud_resource_orchestration/__init__.py
cloud_governance/cloud_resource_orchestration/clouds/__init__.py
cloud_governance/cloud_resource_orchestration/clouds/aws/__init__.py
cloud_governance/cloud_resource_orchestration/clouds/aws/ec2/__init__.py
cloud_governance/cloud_resource_orchestration/clouds/aws/ec2/aws_monitor_tickets.py
cloud_governance/cloud_resource_orchestration/clouds/aws/ec2/aws_tagging_operations.py
cloud_governance/cloud_resource_orchestration/clouds/aws/ec2/collect_cro_reports.py
cloud_governance/cloud_resource_orchestration/clouds/aws/ec2/cost_over_usage.py
cloud_governance/cloud_resource_orchestration/clouds/aws/ec2/monitor_cro_instances.py
cloud_governance/cloud_resource_orchestration/clouds/aws/ec2/run_cro.py
cloud_governance/cloud_resource_orchestration/clouds/aws/ec2/tag_cro_instances.py
cloud_governance/cloud_resource_orchestration/clouds/azure/__init__.py
cloud_governance/cloud_resource_orchestration/clouds/azure/resource_groups/__init__.py
cloud_governance/cloud_resource_orchestration/clouds/azure/resource_groups/abstract_resource.py
cloud_governance/cloud_resource_orchestration/clouds/azure/resource_groups/azure_monitor_tickets.py
cloud_governance/cloud_resource_orchestration/clouds/azure/resource_groups/azure_tagging_operations.py
cloud_governance/cloud_resource_orchestration/clouds/azure/resource_groups/collect_cro_reports.py
cloud_governance/cloud_resource_orchestration/clouds/azure/resource_groups/cost_over_usage.py
cloud_governance/cloud_resource_orchestration/clouds/azure/resource_groups/monitor_cro_resources.py
cloud_governance/cloud_resource_orchestration/clouds/azure/resource_groups/tag_cro_resources.py
cloud_governance/cloud_resource_orchestration/clouds/common/__init__.py
cloud_governance/cloud_resource_orchestration/clouds/common/abstract_collect_cro_reports.py
cloud_governance/cloud_resource_orchestration/clouds/common/abstract_cost_over_usage.py
cloud_governance-1.1.392.dist-info/licenses/LICENSE
cloud_governance-1.1.392.dist-info/METADATA
cloud_governance-1.1.392.dist-info/WHEEL
cloud_governance-1.1.392.dist-info/top_level.txt
cloud_governance-1.1.392.dist-info/RECORD
