Metadata-Version: 2.4
Name: cloud-governance
Version: 1.1.392
Summary: Cloud Governance Tool
Home-page: https://github.com/redhat-performance/cloud-governance
Author: Red Hat
Author-email: ebattat@redhat.com, athiruma@redhat.com
License: Apache License 2.0
Classifier: License :: OSI Approved :: Apache Software License
Classifier: Programming Language :: Python :: 3
Classifier: Programming Language :: Python :: 3.8
Classifier: Programming Language :: Python :: 3.9
Classifier: Programming Language :: Python :: 3.10
Classifier: Programming Language :: Python :: 3.11
Classifier: Programming Language :: Python :: 3.12
License-File: LICENSE
Requires-Dist: aiohttp==3.10.11
Requires-Dist: attrs==21.4.0
Requires-Dist: azure-identity==1.16.1
Requires-Dist: azure-mgmt-billing==6.0.0
Requires-Dist: azure-mgmt-costmanagement==3.0.0
Requires-Dist: azure-mgmt-subscription==3.1.1
Requires-Dist: azure-mgmt-resource==23.0.1
Requires-Dist: azure-mgmt-compute==30.1.0
Requires-Dist: azure-mgmt-network==25.0.0
Requires-Dist: azure-mgmt-monitor==6.0.2
Requires-Dist: boto3==1.33.1
Requires-Dist: botocore==1.33.8
Requires-Dist: elasticsearch-dsl==7.4.0
Requires-Dist: elasticsearch==7.13.4
Requires-Dist: google-api-python-client==2.57.0
Requires-Dist: google-auth-httplib2==0.1.0
Requires-Dist: google-auth-oauthlib==0.5.2
Requires-Dist: google-cloud-bigquery==3.5.0
Requires-Dist: google-cloud-billing==1.9.1
Requires-Dist: ibm-cloud-sdk-core==3.18.0
Requires-Dist: ibm-cos-sdk==2.13.6
Requires-Dist: ibm-platform-services==0.27.0
Requires-Dist: ibm-schematics==1.1.0
Requires-Dist: ibm-vpc==0.21.0
Requires-Dist: myst-parser==1.0.0
Requires-Dist: numpy<=1.26.4
Requires-Dist: oauthlib~=3.1.1
Requires-Dist: pandas
Requires-Dist: PyAthena[Pandas]==3.0.5
Requires-Dist: PyGitHub==1.55
Requires-Dist: python-ldap==3.4.2
Requires-Dist: requests==2.32.2
Requires-Dist: retry==0.9.2
Requires-Dist: setuptools
Requires-Dist: SoftLayer==6.0.0
Requires-Dist: sphinx-rtd-theme==1.0.0
Requires-Dist: sphinx==5.0.0
Requires-Dist: typeguard==2.13.3
Requires-Dist: typing==3.7.4.3
Requires-Dist: urllib3==1.26.19
Dynamic: author
Dynamic: author-email
Dynamic: classifier
Dynamic: description
Dynamic: description-content-type
Dynamic: home-page
Dynamic: license
Dynamic: license-file
Dynamic: requires-dist
Dynamic: summary
